s3file/__init__.py
s3file/openers.py
s3file/s3file.py
s3file-0.0.0.dist-info/DESCRIPTION.rst
s3file-0.0.0.dist-info/METADATA
s3file-0.0.0.dist-info/RECORD
s3file-0.0.0.dist-info/WHEEL
s3file-0.0.0.dist-info/metadata.json
s3file-0.0.0.dist-info/top_level.txt
test/__init__.py
test/test_s3file.py
