Metadata-Version: 2.0
Name: s3file
Version: 0.0.0
Summary: Python file-like proxy for opening s3 files
Home-page: https://github.com/nackjicholson/s3file
Author: nackjicholson
Author-email: UNKNOWN
License: MIT
Keywords: s3 file aws s3file fs
Platform: UNKNOWN
Requires-Dist: boto3 (<2,>=1)
Requires-Dist: botocore (<2,>=1)
Requires-Dist: six (>=1)
